<annotation>
	<folder>dataset</folder>
	<filename>Paul_1736.jpeg</filename>
	<path>C:\dataset\Paul_1736.jpeg</path>
	<source>
		<database>Unknown</database>
	</source>
	<size>
		<width>704</width>
		<height>382</height>
		<depth>3</depth>
	</size>
	<segmented>0</segmented>
	<object>
		<name>number_plate</name>
		<pose>Unspecified</pose>
		<truncated>0</truncated>
		<difficult>0</difficult>
		<bndbox>
			<xmin>2</xmin>
			<ymin>2</ymin>
			<xmax>700</xmax>
			<ymax>172</ymax>
		</bndbox>
	</object>
	<object>
		<name>number_plate</name>
		<pose>Unspecified</pose>
		<truncated>0</truncated>
		<difficult>0</difficult>
		<bndbox>
			<xmin>4</xmin>
			<ymin>211</ymin>
			<xmax>701</xmax>
			<ymax>381</ymax>
		</bndbox>
	</object>
</annotation>
