<annotation>
	<folder>dataset</folder>
	<filename>Paul_1697.jpg</filename>
	<path>C:\dataset\Paul_1697.jpg</path>
	<source>
		<database>Unknown</database>
	</source>
	<size>
		<width>650</width>
		<height>400</height>
		<depth>3</depth>
	</size>
	<segmented>0</segmented>
	<object>
		<name>number_plate</name>
		<pose>Unspecified</pose>
		<truncated>0</truncated>
		<difficult>0</difficult>
		<bndbox>
			<xmin>446</xmin>
			<ymin>222</ymin>
			<xmax>540</xmax>
			<ymax>258</ymax>
		</bndbox>
	</object>
</annotation>
